drf_jsonmask/__init__.py
drf_jsonmask/constants.py
drf_jsonmask/decorators.py
drf_jsonmask/serializers.py
drf_jsonmask/utils.py
drf_jsonmask/views.py
drf_jsonmask-0.4.0.dist-info/METADATA
drf_jsonmask-0.4.0.dist-info/WHEEL
drf_jsonmask-0.4.0.dist-info/licenses/LICENSE
drf_jsonmask-0.4.0.dist-info/RECORD
