Metadata-Version: 2.1
Name: drf-jsonmask
Version: 0.4.0
Summary: Implements Google's partial response in Django RestFramework (Fork from Zapier's package)
Project-URL: Repository, https://github.com/jllorencetti/drf-jsonmask.git
Author-email: Craig Labenz <craig.labenz@zapier.com>, João Luiz Lorencetti <jll.linux@gmail.com>
Maintainer-email: Christian Hartung <hartungstenio@outlook.com>
License: Copyright (c) 2018, Craig Labenz <craig@zapier.com>
License-File: LICENSE
Classifier: Development Status :: 4 - Beta
Classifier: Environment :: Web Environment
Classifier: Framework :: Django
Classifier: Framework :: Django :: 4.2
Classifier: Framework :: Django :: 5.0
Classifier: Intended Audience :: Developers
Classifier: License :: OSI Approved :: BSD License
Classifier: Natural Language :: English
Classifier: Operating System :: OS Independent
Classifier: Programming Language :: Python :: 3 :: Only
Classifier: Programming Language :: Python :: 3.8
Classifier: Programming Language :: Python :: 3.9
Classifier: Programming Language :: Python :: 3.10
Classifier: Programming Language :: Python :: 3.11
Classifier: Programming Language :: Python :: 3.12
Classifier: Topic :: Internet :: WWW/HTTP
Classifier: Topic :: Software Development :: Libraries :: Python Modules
Requires-Python: >=3.8
Requires-Dist: django>=4.2
Requires-Dist: djangorestframework>=3.14
Requires-Dist: jsonmask
